[
  {
    "ip": "192.168.68.239",
    "ports": [
      22,
      80,
      443
    ]
  },
  {
    "ip": "192.168.85.206",
    "ports": [
      22,
      80,
      443
    ]
  },
  {
    "ip": "192.168.121.128",
    "ports": [
      22,
      80,
      443
    ]
  },
  {
    "ip": "192.168.65.8",
    "ports": [
      22,
      80,
      443
    ]
  },
  {
    "ip": "192.168.99.253",
    "ports": [
      22,
      80,
      443
    ]
  },
  {
    "ip": "192.168.198.158",
    "ports": [
      22,
      80,
      443
    ]
  }
]